{"inkVersion":20,"root":[["ev","str","^River","/str",{"x()":"Name","exArgs":1},"out","/ev","\n","^Hey guys! I have something exciting to tell you! Are you ready?","\n","ev","str","^Skyler","/str",{"x()":"Name","exArgs":1},"out","/ev","\n","^Oh?","\n","ev","str","^Robin","/str",{"x()":"Name","exArgs":1},"out","/ev","\n","^Here we go...","\n","ev","str","^River","/str",{"x()":"Name","exArgs":1},"out","/ev","\n","^So there’s this haun- I mean, a cool creek I’ve overheard my brother talking about with his friends! We should check it out! What do you say? It’s the summer break!","\n","ev","str","^Skyler","/str",{"x()":"Name","exArgs":1},"out","/ev","\n","^…","\n","ev","str","^Robin","/str",{"x()":"Name","exArgs":1},"out","/ev","\n","^What's the location again?","\n","ev","str","^River","/str",{"x()":"Name","exArgs":1},"out","/ev","\n","^Someplace... near, the nearby village. Quite near but not to... near.","\n","ev","str","^Robin","/str",{"x()":"Name","exArgs":1},"out","/ev","\n","^Okay so first off, you absolutely hate water. Secondly, your number of “near”s is fishy. Are you referring to the west area that no one really goes to? The Salamander Creek??","\n","ev","str","^Skyler","/str",{"x()":"Name","exArgs":1},"out","/ev","\n","^Oh no...","\n","ev","str","^River","/str",{"x()":"Name","exArgs":1},"out","/ev","\n","^Listen. Yes, alright. I’ve heard my brother’s friend Oly bragging about finding a so-called monster there... And I...really wanna see it. To be fair, he came back alive right?? Trust me, I w-wouldn’t have asked you to join me if it was dangerous.","\n","ev","str","^Robin","/str",{"x()":"Name","exArgs":1},"out","/ev","\n","^... your brother refused to go with you, didn’t he?...","\n","ev","str","^River","/str",{"x()":"Name","exArgs":1},"out","/ev","\n","^See, when was the last time we’ve done something exciting? Are you scared or something?","\n","ev","str","^Skyler","/str",{"x()":"Name","exArgs":1},"out","/ev","\n","^Yes.","\n","ev","str","^Robin","/str",{"x()":"Name","exArgs":1},"out","/ev","\n","^Of course not! I don’t believe in paranormal hocus pocus.","\n","ev","str","^River","/str",{"x()":"Name","exArgs":1},"out","/ev","\n","^Then let’s go! I’ll prove you wrong!","\n","ev","str","^Robin","/str",{"x()":"Name","exArgs":1},"out","/ev","\n","^And I bet we’ll find nothing there! It’s just gonna be full of Salamanders.","\n","ev","str","^Skyler","/str",{"x()":"Name","exArgs":1},"out","/ev","\n","^oh no...","\n","ev","str","^Robin","/str",{"x()":"Name","exArgs":1},"out","/ev","\n","^Come on Skyler, it’ll be fine. Salamanders are not dangerous.","\n","ev","str","^Skyler","/str",{"x()":"Name","exArgs":1},"out","/ev","\n","^... okay.","\n","ev","str","^River","/str",{"x()":"Name","exArgs":1},"out","/ev","\n","^YES!","\n",["done",{"#f":5,"#n":"g-0"}],null],"done",{"#f":1}],"listDefs":{}}